<?xml version="1.0" encoding="UTF-8"?><record_update>
    <sys_choice action="INSERT_OR_UPDATE" field="direction" table="x_15500_integrate_action" version="3">
        <sys_choice_set action="INSERT_OR_UPDATE">
            <element>direction</element>
            <name>x_15500_integrate_action</name>
            <sys_class_name>sys_choice_set</sys_class_name>
            <sys_created_by>admin</sys_created_by>
            <sys_created_on>2022-06-21 18:15:38</sys_created_on>
            <sys_id>80a624a487d011108bc2da873cbb355c</sys_id>
            <sys_mod_count>0</sys_mod_count>
            <sys_name>direction</sys_name>
            <sys_package display_value="Integration One" source="x_15500_integrate">8c5c7296873301108bc2da873cbb35f2</sys_package>
            <sys_policy/>
            <sys_scope display_value="Integration One">8c5c7296873301108bc2da873cbb35f2</sys_scope>
            <sys_update_name>sys_choice_x_15500_integrate_action_direction</sys_update_name>
            <sys_updated_by>admin</sys_updated_by>
            <sys_updated_on>2022-06-21 18:15:38</sys_updated_on>
        </sys_choice_set>
        <sys_choice action="INSERT_OR_UPDATE">
            <dependent_value/>
            <element>direction</element>
            <hint/>
            <inactive>false</inactive>
            <label>Inbound</label>
            <language>en</language>
            <name>x_15500_integrate_action</name>
            <sequence>1</sequence>
            <synonyms/>
            <sys_created_by>admin</sys_created_by>
            <sys_created_on>2022-06-21 18:15:38</sys_created_on>
            <sys_domain>global</sys_domain>
            <sys_domain_path>/</sys_domain_path>
            <sys_id>329620a487d011108bc2da873cbb353c</sys_id>
            <sys_mod_count>2</sys_mod_count>
            <sys_updated_by>admin</sys_updated_by>
            <sys_updated_on>2022-06-21 18:15:44</sys_updated_on>
            <value>inbound</value>
        </sys_choice>
        <sys_choice action="INSERT_OR_UPDATE">
            <dependent_value/>
            <element>direction</element>
            <hint/>
            <inactive>false</inactive>
            <label>Outbound</label>
            <language>en</language>
            <name>x_15500_integrate_action</name>
            <sequence>2</sequence>
            <synonyms/>
            <sys_created_by>admin</sys_created_by>
            <sys_created_on>2022-06-21 18:15:49</sys_created_on>
            <sys_domain>global</sys_domain>
            <sys_domain_path>/</sys_domain_path>
            <sys_id>80a664a487d011108bc2da873cbb354c</sys_id>
            <sys_mod_count>2</sys_mod_count>
            <sys_updated_by>admin</sys_updated_by>
            <sys_updated_on>2022-06-21 18:15:56</sys_updated_on>
            <value>outbound</value>
        </sys_choice>
    </sys_choice>
</record_update>
